basic_sftp/__init__.py
basic_sftp/basic_sftp.py
basic_sftp/cli.py
basic_sftp-1.3.6.dist-info/AUTHORS.rst
basic_sftp-1.3.6.dist-info/METADATA
basic_sftp-1.3.6.dist-info/WHEEL
basic_sftp-1.3.6.dist-info/entry_points.txt
basic_sftp-1.3.6.dist-info/top_level.txt
basic_sftp-1.3.6.dist-info/RECORD
