Metadata-Version: 2.1
Name: basic-sftp
Version: 1.3.6
Summary: This projects creates a basic sftp connection that allows you to send any document to a digital ocean server
Home-page: https://github.com/blegarth/basic_sftp
Author: Brian Legarth
Author-email: legarth7@gmail.com
License: UNKNOWN
Keywords: basic_sftp
Platform: UNKNOWN
Classifier: Development Status :: 2 - Pre-Alpha
Classifier: Intended Audience :: Developers
Classifier: Natural Language :: English
Classifier: Programming Language :: Python :: 3
Classifier: Programming Language :: Python :: 3.5
Classifier: Programming Language :: Python :: 3.6
Classifier: Programming Language :: Python :: 3.7
Classifier: Programming Language :: Python :: 3.8
Requires-Python: >=3.5
Requires-Dist: Click (>=7.0)
Requires-Dist: pysftp
